README
setup.cfg
setup.py
mkv/__init__.py
mkv/merge.py
mkv/source.py
mkv.egg-info/PKG-INFO
mkv.egg-info/SOURCES.txt
mkv.egg-info/dependency_links.txt
mkv.egg-info/not-zip-safe
mkv.egg-info/top_level.txt