Metadata-Version: 1.1
Name: mkv
Version: 0.1.4
Summary: Merge and split mkv files usign mkvextract and mkvmerge.
Home-page: https://bitbucket.org/Nekmo/python-mkv
Author: Nekmo
Author-email: contacto@nekmo.com
License: UNKNOWN
Download-URL: https://bitbucket.org/Nekmo/nekbot.protocols.irc/get/default.tar.gz
Keywords: python,mkv,extract,merge,join
Platform: any
Classifier: Development Status :: 1 - Planning
Classifier: License :: OSI Approved :: MIT License
Classifier: Intended Audience :: Developers
Classifier: Environment :: Console
Classifier: Topic :: Multimedia :: Video
Classifier: Programming Language :: Python
Classifier: Programming Language :: Python :: 2
Classifier: Programming Language :: Python :: 2.6
Classifier: Programming Language :: Python :: 2.7
Classifier: Programming Language :: Python :: 3
Classifier: Programming Language :: Python :: 3.2
Classifier: Programming Language :: Python :: 3.3
Classifier: Programming Language :: Python :: 3.4
